Metadata-Version: 2.1
Name: gitlab-duration-parser
Version: 1.0.1
Summary: A simple Gitlab time-tracking message parser
Home-page: https://github.com/florczakraf/gitlab-duration-parser
Author: Rafał Florczak
Author-email: florczak.raf+gitlabdurationparser@gmail.com
License: UNKNOWN
Platform: UNKNOWN
Classifier: Programming Language :: Python :: 2
Classifier: Programming Language :: Python :: 3
Classifier: Operating System :: OS Independent
